<?xml version="1.0" encoding="UTF-8"?><record_update table="question_choice">
    <question_choice action="DELETE">
        <inactive>true</inactive>
        <misc>0</misc>
        <order>100</order>
        <published_ref/>
        <question display_value="Decision">69d12c02878b30502e1641d8cebb35d3</question>
        <rec_misc>0</rec_misc>
        <sys_class_name>question_choice</sys_class_name>
        <sys_created_by>V849486</sys_created_by>
        <sys_created_on>2021-10-08 10:47:01</sys_created_on>
        <sys_customer_update>false</sys_customer_update>
        <sys_id>21e82c0a878b30502e1641d8cebb35fa</sys_id>
        <sys_mod_count>0</sys_mod_count>
        <sys_name/>
        <sys_package display_value="Probationary Employee Management" source="x_unhi_probationar">b2d1b39d1b0f74505e83ff7e034bcb20</sys_package>
        <sys_policy/>
        <sys_replace_on_upgrade>false</sys_replace_on_upgrade>
        <sys_scope display_value="Probationary Employee Management">b2d1b39d1b0f74505e83ff7e034bcb20</sys_scope>
        <sys_update_name>question_choice_21e82c0a878b30502e1641d8cebb35fa</sys_update_name>
        <sys_updated_by>V849486</sys_updated_by>
        <sys_updated_on>2021-10-08 10:47:01</sys_updated_on>
        <text/>
        <value/>
    </question_choice>
    <fx_price action="DELETE" query="id=21e82c0a878b30502e1641d8cebb35fa"/>
    <fx_price action="DELETE">
        <amount>0</amount>
        <currency display_value="USD">USD</currency>
        <field>misc</field>
        <id>21e82c0a878b30502e1641d8cebb35fa</id>
        <parent/>
        <reference_amount>0</reference_amount>
        <reference_currency display_value="USD">USD</reference_currency>
        <sys_created_by>V849486</sys_created_by>
        <sys_created_on>2021-10-08 10:47:01</sys_created_on>
        <sys_id>e0f8644a878b30502e1641d8cebb3562</sys_id>
        <sys_mod_count>0</sys_mod_count>
        <sys_updated_by>V849486</sys_updated_by>
        <sys_updated_on>2021-10-08 10:47:01</sys_updated_on>
        <table>question_choice</table>
        <type>calculated</type>
    </fx_price>
    <fx_price action="DELETE">
        <amount>0</amount>
        <currency display_value="USD">USD</currency>
        <field>rec_misc</field>
        <id>21e82c0a878b30502e1641d8cebb35fa</id>
        <parent/>
        <reference_amount>0</reference_amount>
        <reference_currency display_value="USD">USD</reference_currency>
        <sys_created_by>V849486</sys_created_by>
        <sys_created_on>2021-10-08 10:47:01</sys_created_on>
        <sys_id>64f8644a878b30502e1641d8cebb3561</sys_id>
        <sys_mod_count>0</sys_mod_count>
        <sys_updated_by>V849486</sys_updated_by>
        <sys_updated_on>2021-10-08 10:47:01</sys_updated_on>
        <table>question_choice</table>
        <type>calculated</type>
    </fx_price>
    <sys_update_version action="INSERT_OR_UPDATE">
        <action>DELETE</action>
        <application display_value="Probationary Employee Management">b2d1b39d1b0f74505e83ff7e034bcb20</application>
        <file_path/>
        <instance_id>f4897907db2f32c4536ad5b0cf9619a0</instance_id>
        <instance_name>uniteddevnext</instance_name>
        <name>question_choice_21e82c0a878b30502e1641d8cebb35fa</name>
        <payload><![CDATA[<?xml version="1.0" encoding="UTF-8"?><record_update table="question_choice"><question_choice action="INSERT_OR_UPDATE"><inactive>true</inactive><misc>0</misc><order>100</order><published_ref/><question display_value="Decision">69d12c02878b30502e1641d8cebb35d3</question><rec_misc>0</rec_misc><sys_class_name>question_choice</sys_class_name><sys_created_by>V849486</sys_created_by><sys_created_on>2021-10-08 10:47:01</sys_created_on><sys_customer_update>false</sys_customer_update><sys_id>21e82c0a878b30502e1641d8cebb35fa</sys_id><sys_mod_count>0</sys_mod_count><sys_name/><sys_package display_value="Probationary Employee Management" source="x_unhi_probationar">b2d1b39d1b0f74505e83ff7e034bcb20</sys_package><sys_policy/><sys_replace_on_upgrade>false</sys_replace_on_upgrade><sys_scope display_value="Probationary Employee Management">b2d1b39d1b0f74505e83ff7e034bcb20</sys_scope><sys_update_name>question_choice_21e82c0a878b30502e1641d8cebb35fa</sys_update_name><sys_updated_by>V849486</sys_updated_by><sys_updated_on>2021-10-08 10:47:01</sys_updated_on><text/><value/></question_choice><fx_price action="delete_multiple" query="id=21e82c0a878b30502e1641d8cebb35fa"/><fx_price action="INSERT_OR_UPDATE"><amount>0</amount><currency display_value="USD">USD</currency><field>misc</field><id>21e82c0a878b30502e1641d8cebb35fa</id><parent/><reference_amount>0</reference_amount><reference_currency display_value="USD">USD</reference_currency><sys_created_by>V849486</sys_created_by><sys_created_on>2021-10-08 10:47:01</sys_created_on><sys_id>e0f8644a878b30502e1641d8cebb3562</sys_id><sys_mod_count>0</sys_mod_count><sys_updated_by>V849486</sys_updated_by><sys_updated_on>2021-10-08 10:47:01</sys_updated_on><table>question_choice</table><type>calculated</type></fx_price><fx_price action="INSERT_OR_UPDATE"><amount>0</amount><currency display_value="USD">USD</currency><field>rec_misc</field><id>21e82c0a878b30502e1641d8cebb35fa</id><parent/><reference_amount>0</reference_amount><reference_currency display_value="USD">USD</reference_currency><sys_created_by>V849486</sys_created_by><sys_created_on>2021-10-08 10:47:01</sys_created_on><sys_id>64f8644a878b30502e1641d8cebb3561</sys_id><sys_mod_count>0</sys_mod_count><sys_updated_by>V849486</sys_updated_by><sys_updated_on>2021-10-08 10:47:01</sys_updated_on><table>question_choice</table><type>calculated</type></fx_price></record_update>]]></payload>
        <payload_hash>49413773</payload_hash>
        <record_name/>
        <reverted_from/>
        <source>bed1b39d1b0f74505e83ff7e034bcb22</source>
        <source_table>sys_update_set</source_table>
        <state>previous</state>
        <sys_created_by>V849486</sys_created_by>
        <sys_created_on>2021-10-08 10:47:01</sys_created_on>
        <sys_id>24f8644a878b30502e1641d8cebb3564</sys_id>
        <sys_mod_count>0</sys_mod_count>
        <sys_recorded_at>17c5f836ce50000001</sys_recorded_at>
        <sys_updated_by>V849486</sys_updated_by>
        <sys_updated_on>2021-10-08 10:47:01</sys_updated_on>
        <type>Question Choice</type>
        <update_guid>2cf8644ad78b30507da80dc361484f63</update_guid>
        <update_guid_history>2cf8644ad78b30507da80dc361484f63:49413773</update_guid_history>
    </sys_update_version>
    <sys_metadata_delete action="INSERT_OR_UPDATE">
        <sys_audit_delete display_value="Record deleted 2021-10-08 05:47:12">9bf8ec0a878b30502e1641d8cebb3556</sys_audit_delete>
        <sys_class_name>sys_metadata_delete</sys_class_name>
        <sys_created_by>V849486</sys_created_by>
        <sys_created_on>2021-10-08 10:47:12</sys_created_on>
        <sys_customer_update>false</sys_customer_update>
        <sys_db_object display_value="" name="question_choice">question_choice</sys_db_object>
        <sys_id>0d15a5123862410e814f2b6e1d3e7464</sys_id>
        <sys_metadata>21e82c0a878b30502e1641d8cebb35fa</sys_metadata>
        <sys_mod_count>0</sys_mod_count>
        <sys_name/>
        <sys_package display_value="Probationary Employee Management" source="x_unhi_probationar">b2d1b39d1b0f74505e83ff7e034bcb20</sys_package>
        <sys_parent display_value="Overall Decision Rating">69d12c02878b30502e1641d8cebb35d3</sys_parent>
        <sys_policy/>
        <sys_replace_on_upgrade>false</sys_replace_on_upgrade>
        <sys_scope display_value="Probationary Employee Management">b2d1b39d1b0f74505e83ff7e034bcb20</sys_scope>
        <sys_scope_delete display_value="">06ef1fca416f4688b04555b7afbddc99</sys_scope_delete>
        <sys_update_name>question_choice_21e82c0a878b30502e1641d8cebb35fa</sys_update_name>
        <sys_update_version display_value="question_choice_21e82c0a878b30502e1641d8cebb35fa">24f8644a878b30502e1641d8cebb3564</sys_update_version>
        <sys_updated_by>V849486</sys_updated_by>
        <sys_updated_on>2021-10-08 10:47:12</sys_updated_on>
    </sys_metadata_delete>
</record_update>
